gcal_manager/__init__.py
gcal_manager/account.py
gcal_manager/calendar.py
gcal_manager/context.py
gcal_manager/event.py
gcal_manager/task.py
gcal_manager-0.1.0.dist-info/LICENSE
gcal_manager-0.1.0.dist-info/METADATA
gcal_manager-0.1.0.dist-info/WHEEL
gcal_manager-0.1.0.dist-info/RECORD
