Metadata-Version: 2.1
Name: gcal-manager
Version: 0.1.0
Summary: 
Home-page: https://github.com/jenscobie/gcal-manager
License: MIT
Author: Jen Scobie
Author-email: jenscobie@gmail.com
Requires-Python: >=3.13,<4.0
Classifier: License :: OSI Approved :: MIT License
Classifier: Programming Language :: Python :: 3
Classifier: Programming Language :: Python :: 3.13
Requires-Dist: arguably (>=1.3.0,<2.0.0)
Project-URL: Repository, https://github.com/jenscobie/gcal-manager
